volgactf.final-3.0.0-py3.13-nspkg.pth
volgactf/final/__about__.py
volgactf/final/__init__.py
volgactf/final/capsule_api.py
volgactf/final/flag_api.py
volgactf/final/service_api.py
volgactf_final-3.0.0.dist-info/licenses/LICENSE
volgactf_final-3.0.0.dist-info/METADATA
volgactf_final-3.0.0.dist-info/WHEEL
volgactf_final-3.0.0.dist-info/entry_points.txt
volgactf_final-3.0.0.dist-info/namespace_packages.txt
volgactf_final-3.0.0.dist-info/top_level.txt
volgactf_final-3.0.0.dist-info/RECORD
