Metadata-Version: 2.4
Name: volgactf.final
Version: 3.0.0
Summary: VolgaCTF Final CLI & public API library
Home-page: https://github.com/VolgaCTF/volgactf-final-py
Author: VolgaCTF
Author-email: it@volgactf.ru
License: MIT
Classifier: Programming Language :: Python :: 3
Classifier: Programming Language :: Python :: 3.9
Classifier: Programming Language :: Python :: 3.10
Classifier: Programming Language :: Python :: 3.11
Classifier: Programming Language :: Python :: 3.12
Classifier: Programming Language :: Python :: 3.13
Requires-Python: >=3.9
License-File: LICENSE
Requires-Dist: setuptools>=35.0.0
Requires-Dist: requests>=2.18.4
Requires-Dist: grequests==0.3.0
Requires-Dist: click>=6.7
Requires-Dist: python-dateutil>=2.6.0
Requires-Dist: PyJWT>=2.4.0
Requires-Dist: cryptography>=2.3.0
Dynamic: author
Dynamic: author-email
Dynamic: classifier
Dynamic: home-page
Dynamic: license
Dynamic: license-file
Dynamic: requires-dist
Dynamic: requires-python
Dynamic: summary
